jsp_instance_utils/__init__.py
jsp_instance_utils/instance_parser.py
jsp_instance_utils/instances.py
jsp_instance_utils/jsp_instance_generator.py
jsp_instance_utils/jsp_or_tools_solver.py
jsp_instance_utils-1.0.4.dist-info/METADATA
jsp_instance_utils-1.0.4.dist-info/WHEEL
jsp_instance_utils-1.0.4.dist-info/top_level.txt
jsp_instance_utils-1.0.4.dist-info/RECORD
