Metadata-Version: 2.4
Name: jsp-instance-utils
Version: 1.0.4
Summary: A package containing benchmark instances for the Job Shop Scheduling Problem (JSP) scraped from various sources.
Author: Alexander Nasuta
Author-email: Alexander Nasuta <alexander.nasuta@wzl-iqs.rwth-aachen.de>
License: MIT
Project-URL: Homepage, https://github.com/Alexander-Nasuta/jsp-instance-utils/
Platform: unix
Platform: linux
Platform: osx
Platform: cygwin
Platform: win32
Classifier: Programming Language :: Python
Classifier: Programming Language :: Python :: 3
Requires-Python: >=3.11
Requires-Dist: requests
Requires-Dist: numpy
Requires-Dist: ortools
Requires-Dist: beautifulsoup4
Requires-Dist: jsp-vis
Provides-Extra: dev
Requires-Dist: pip-tools; extra == "dev"
Requires-Dist: pytest; extra == "dev"
Requires-Dist: pytest-cov; extra == "dev"
Requires-Dist: tox; extra == "dev"
Requires-Dist: twine; extra == "dev"
Requires-Dist: gym; extra == "dev"
Requires-Dist: gymnasium; extra == "dev"
Requires-Dist: JSSEnv; extra == "dev"
Requires-Dist: graph-jsp-env; extra == "dev"
Requires-Dist: graph-matrix-jsp-env; extra == "dev"
Requires-Dist: sphinx; extra == "dev"
Requires-Dist: myst-parser; extra == "dev"
Requires-Dist: sphinx-autobuild; extra == "dev"
Requires-Dist: nbsphinx; extra == "dev"
Requires-Dist: furo; extra == "dev"
Requires-Dist: twine; extra == "dev"
Requires-Dist: sphinx-copybutton; extra == "dev"
Requires-Dist: nbsphinx; extra == "dev"
Requires-Dist: pandoc; extra == "dev"
Requires-Dist: jupytext; extra == "dev"
Requires-Dist: notebook; extra == "dev"
Requires-Dist: typing_extensions>=4.12.0; extra == "dev"
